[
  {
    "title": "I Can Go Online : A gentle introduction to staying safe online",
    "author": "Talemaimaleya, Becca",
    "publisher": "Becca's Children's Books",
    "format": "Paperback / softback",
    "pubDate": "6 Apr 2024",
    "isbn": "9781915822185",
    "dewey": "004.678083",
    "rrp": "",
    "link": "https://www.brownsbfs.co.uk/Product/Talemaimaleya-Becca/I-Can-Go-Online/9781915822185"
  },
  {
    "title": "Foundations of Software Science and Computation Structures : 27th International Conference, FoSSaCS 2024, Held as Part of the European Joint Conferences on Theory and Practice of Software, ETAPS 2024, Luxembourg City, Luxembourg, April 6–11, 2024, Proceedings, Part II",
    "author": "Kobayashi, Naoki",
    "publisher": "Springer International Publishing AG",
    "format": "Paperback / softback",
    "pubDate": "6 Apr 2024",
    "isbn": "9783031572302",
    "dewey": "005",
    "rrp": "£34.99",
    "link": "https://www.brownsbfs.co.uk/Product/Kobayashi-Naoki/Foundations-of-Software-Science-and-Computation-Structures/9783031572302"
  },
  {
    "title": "Fundamental Approaches to Software Engineering : 27th International Conference, FASE 2024, Held as Part of the European Joint Conferences on Theory and Practice of Software, ETAPS 2024, Luxembourg City, Luxembourg, April 6–11, 2024, Proceedings",
    "author": "Beyer, Dirk, Ph. D.",
    "publisher": "Springer International Publishing AG",
    "format": "Paperback / softback",
    "pubDate": "6 Apr 2024",
    "isbn": "9783031572586",
    "dewey": "005.1",
    "rrp": "",
    "link": "https://www.brownsbfs.co.uk/Product/Beyer-Dirk-Ph-D/Fundamental-Approaches-to-Software-Engineering/9783031572586"
  },
  {
    "title": "Generative AI Security : Theories and Practices",
    "author": "Huang, Ken",
    "publisher": "Springer International Publishing AG",
    "format": "Hardback",
    "pubDate": "6 Apr 2024",
    "isbn": "9783031542510",
    "dewey": "005.8",
    "rrp": "£89.99",
    "link": "https://www.brownsbfs.co.uk/Product/Huang-Ken/Generative-AI-Security/9783031542510"
  },
  {
    "title": "Pan-African Conference on Artificial Intelligence: Second Conference, PanAfriCon AI 2023, Addis Ababa, Ethiopia, October 5-6, 2023, Revised Selected Papers, Part I : Second Conference, PanAfriCon AI 2023, Addis Ababa, Ethiopia, October 5-6, 2023, Revised Selected Papers, Part I - 2068",
    "author": "Debelee, Taye Girma",
    "publisher": "Springer",
    "format": "Ebook",
    "pubDate": "6 Apr 2024",
    "isbn": "9783031576249",
    "dewey": "006.3",
    "rrp": "",
    "link": "https://www.brownsbfs.co.uk/Product/Debelee-Taye-Girma/Pan-African-Conference-on-Artificial-Intelligence-Second-/9783031576249"
  },
  {
    "title": "AI Technologies and Virtual Reality : Proceedings of 7th International Conference on Artificial Intelligence and Virtual Reality (AIVR 2023)",
    "author": "Nakamatsu, Kazumi",
    "publisher": "Springer Verlag, Singapore",
    "format": "Hardback",
    "pubDate": "6 Apr 2024",
    "isbn": "9789819990177",
    "dewey": "006.3",
    "rrp": "£199.99",
    "link": "https://www.brownsbfs.co.uk/Product/Nakamatsu-Kazumi/AI-Technologies-and-Virtual-Reality/9789819990177"
  },
  {
    "title": "International Symposium on Intelligent Informatics : Proceedings of ISI 2022",
    "author": "Thampi, Sabu M.",
    "publisher": "Springer Verlag, Singapore",
    "format": "Paperback / softback",
    "pubDate": "6 Apr 2024",
    "isbn": "9789811980961",
    "dewey": "006.3",
    "rrp": "£249.99",
    "link": "https://www.brownsbfs.co.uk/Product/Thampi-Sabu-M/International-Symposium-on-Intelligent-Informatics/9789811980961"
  },
  {
    "title": "Accountable and Explainable Methods for Complex Reasoning over Text",
    "author": "Atanasova, Pepa",
    "publisher": "Springer International Publishing AG",
    "format": "Paperback / softback",
    "pubDate": "6 Apr 2024",
    "isbn": "9783031515170",
    "dewey": "006.35",
    "rrp": "",
    "link": "https://www.brownsbfs.co.uk/Product/Atanasova-Pepa/Accountable-and-Explainable-Methods-for-Complex-Reasoning-over-Text/9783031515170"
  },
  {
    "title": "The Affective Core Self : The Role of the Unconscious and Retroactivity in Self-Constitution",
    "author": "Horvath, Lajos",
    "publisher": "Springer International Publishing AG",
    "format": "Hardback",
    "pubDate": "6 Apr 2024",
    "isbn": "9783031569197",
    "dewey": "126",
    "rrp": "",
    "link": "https://www.brownsbfs.co.uk/Product/Horvath-Lajos/The-Affective-Core-Self/9783031569197"
  },
  {
    "title": "Spirit Guides on Speed Dial : A Pragmatic Approach to Getting What You Want",
    "author": "Apollo, Jules",
    "publisher": "Utopian Forest",
    "format": "Paperback / softback",
    "pubDate": "6 Apr 2024",
    "isbn": "9798989159901",
    "dewey": "133.9",
    "rrp": "£17.99",
    "link": "https://www.brownsbfs.co.uk/Product/Apollo-Jules/Spirit-Guides-on-Speed-Dial/9798989159901"
  },
  {
    "title": "Global Perspectives on Precision Medicine : Ethical, Social and Public Health Implications",
    "author": "Sarwar, Evangel",
    "publisher": "Springer International Publishing AG",
    "format": "Paperback / softback",
    "pubDate": "6 Apr 2024",
    "isbn": "9783031285950",
    "dewey": "174.2",
    "rrp": "£109.99",
    "link": "https://www.brownsbfs.co.uk/Product/Sarwar-Evangel/Global-Perspectives-on-Precision-Medicine/9783031285950"
  },
  {
    "title": "Regional Culture and Social Change : A Study of Miao-Inhabited Areas of Southwest China",
    "author": "Ma, Yuhua",
    "publisher": "Springer Verlag, Singapore",
    "format": "Paperback / softback",
    "pubDate": "6 Apr 2024",
    "isbn": "9789811989858",
    "dewey": "305.89597205134",
    "rrp": "£109.99",
    "link": "https://www.brownsbfs.co.uk/Product/Ma-Yuhua/Regional-Culture-and-Social-Change/9789811989858"
  },
  {
    "title": "Mathematics in Politics and Governance",
    "author": "Aragon-Artacho, Francisco J.",
    "publisher": "Springer International Publishing AG",
    "format": "Hardback",
    "pubDate": "6 Apr 2024",
    "isbn": "9783031527753",
    "dewey": "320.01513",
    "rrp": "",
    "link": "https://www.brownsbfs.co.uk/Product/Aragon-Artacho-Francisco-J/Mathematics-in-Politics-and-Governance/9783031527753"
  },
  {
    "title": "Industry 4.0 to Industry 5.0 : Explorations in the Transition from a Techno-economic to a Socio-technical Future",
    "author": "Nousala, Susu",
    "publisher": "Springer Verlag, Singapore",
    "format": "Hardback",
    "pubDate": "6 Apr 2024",
    "isbn": "9789819997299",
    "dewey": "330.1",
    "rrp": "",
    "link": "https://www.brownsbfs.co.uk/Product/Nousala-Susu/Industry-40-to-Industry-50/9789819997299"
  },
  {
    "title": "The Indonesian Economy and the Surrounding Regions in the 21st Century : Essays in Honor of Iwan Jaya Azis",
    "author": "Resosudarmo, Budy Prasetyo",
    "publisher": "Springer Verlag, Singapore",
    "format": "Hardback",
    "pubDate": "6 Apr 2024",
    "isbn": "9789819701216",
    "dewey": "330.9598",
    "rrp": "",
    "link": "https://www.brownsbfs.co.uk/Product/Resosudarmo-Budy-Prasetyo/The-Indonesian-Economy-and-the-Surrounding-Regions-in-the-21st-Century/9789819701216"
  },
  {
    "title": "Sustainable Finances and the Law : Between Public and Private Solutions",
    "author": "Saraiva, Rute",
    "publisher": "Springer International Publishing AG",
    "format": "Hardback",
    "pubDate": "6 Apr 2024",
    "isbn": "9783031494598",
    "dewey": "332",
    "rrp": "",
    "link": "https://www.brownsbfs.co.uk/Product/Saraiva-Rute/Sustainable-Finances-and-the-Law/9783031494598"
  },
  {
    "title": "The Paradox of Intellectual Property in Capitalism",
    "author": "Romeiro  Hermeto, Joao",
    "publisher": "Palgrave Macmillan",
    "format": "Hardback",
    "pubDate": "6 Apr 2024",
    "isbn": "9783031499661",
    "dewey": "338",
    "rrp": "",
    "link": "https://www.brownsbfs.co.uk/Product/Romeiro--Hermeto-Joao/The-Paradox-of-Intellectual-Property-in-Capitalism/9783031499661"
  },
  {
    "title": "Sustainability in Business Education, Research and Practices",
    "author": "Wall, Tony",
    "publisher": "Springer",
    "format": "Ebook",
    "pubDate": "6 Apr 2024",
    "isbn": "9783031559969",
    "dewey": "338.927",
    "rrp": "",
    "link": "https://www.brownsbfs.co.uk/Product/Wall-Tony/Sustainability-in-Business-Education-Research-and-Practices/9783031559969"
  },
  {
    "title": "Modern Money Theory : A Simple Guide to the Monetary System",
    "author": "Ehnts, Dirk",
    "publisher": "Springer International Publishing AG",
    "format": "Hardback",
    "pubDate": "6 Apr 2024",
    "isbn": "9783031535369",
    "dewey": "339.53",
    "rrp": "",
    "link": "https://www.brownsbfs.co.uk/Product/Ehnts-Dirk/Modern-Money-Theory/9783031535369"
  },
  {
    "title": "Theories of Legal Obligation - 146",
    "author": "Beyleveld, Deryck",
    "publisher": "Springer",
    "format": "Ebook",
    "pubDate": "6 Apr 2024",
    "isbn": "9783031540677",
    "dewey": "340.1",
    "rrp": "",
    "link": "https://www.brownsbfs.co.uk/Product/Beyleveld-Deryck/Theories-of-Legal-Obligation/9783031540677"
  },
  {
    "title": "Rene Girard, Law, Literature, and Cinema : The Legal Drama of the Scapegoat",
    "author": "Wilson, Eric M.",
    "publisher": "Springer Verlag, Singapore",
    "format": "Hardback",
    "pubDate": "6 Apr 2024",
    "isbn": "9789819711550",
    "dewey": "340.1",
    "rrp": "",
    "link": "https://www.brownsbfs.co.uk/Product/Wilson-Eric-M/Rene-Girard-Law-Literature-and-Cinema/9789819711550"
  },
  {
    "title": "Digital China: Big Data and Government Managerial Decision",
    "author": "Jiang, Qing",
    "publisher": "Springer Verlag, Singapore",
    "format": "Paperback / softback",
    "pubDate": "6 Apr 2024",
    "isbn": "9789811997174",
    "dewey": "351.028557",
    "rrp": "£109.99",
    "link": "https://www.brownsbfs.co.uk/Product/Jiang-Qing/Digital-China-Big-Data-and-Government-Managerial-Decision/9789811997174"
  },
  {
    "title": "German Structural Pacifism : Cultural Trauma and German Security Policy since Reunification",
    "author": "Verbovszky, Joseph",
    "publisher": "Springer vs",
    "format": "Paperback / softback",
    "pubDate": "6 Apr 2024",
    "isbn": "9783658440893",
    "dewey": "355.033543",
    "rrp": "",
    "link": "https://www.brownsbfs.co.uk/Product/Verbovszky-Joseph/German-Structural-Pacifism/9783658440893"
  },
  {
    "title": "Economy, Society and Politics : Socio-economic and Political Education in Schools and Universities",
    "author": "Fridrich, Christian",
    "publisher": "Springer Fachmedien Wiesbaden",
    "format": "Paperback / softback",
    "pubDate": "6 Apr 2024",
    "isbn": "9783658425241",
    "dewey": "361.1071",
    "rrp": "£69.99",
    "link": "https://www.brownsbfs.co.uk/Product/Fridrich-Christian/Economy-Society-and-Politics/9783658425241"
  },
  {
    "title": "A clinician's survival guide to leadership and management on the ward.",
    "author": "Dolan, Brian",
    "publisher": "Elsevier",
    "format": "Ebook",
    "pubDate": "6 Apr 2024",
    "isbn": "9780443260537",
    "dewey": "362.11",
    "rrp": "",
    "link": "https://www.brownsbfs.co.uk/Product/Dolan-Brian/A-clinicians-survival-guide-to-leadership-and-management-on-the-ward/9780443260537"
  },
  {
    "title": "Access to Mental Health Care in South Asia: Current Status, Potential Challenges, and Ways Out : Current Status, Potential Challenges, and Ways Out",
    "author": "Arafat, S. M. Yasir",
    "publisher": "Springer",
    "format": "Ebook",
    "pubDate": "6 Apr 2024",
    "isbn": "9789819991532",
    "dewey": "362.20954",
    "rrp": "",
    "link": "https://www.brownsbfs.co.uk/Product/Arafat-S-M-Yasir/Access-to-Mental-Health-Care-in-South-Asia-Current-Status/9789819991532"
  },
  {
    "title": "Experts in the World Heritage Regime: Between Protection and Prestige : Between Protection and Prestige",
    "author": "James, Luke",
    "publisher": "Palgrave Macmillan",
    "format": "Ebook",
    "pubDate": "6 Apr 2024",
    "isbn": "9783031554971",
    "dewey": "363.69",
    "rrp": "",
    "link": "https://www.brownsbfs.co.uk/Product/James-Luke/Experts-in-the-World-Heritage-Regime-Between-Protection-and-Prestige/9783031554971"
  },
  {
    "title": "Internationalization and the Academic Profession : Comparative Perspectives",
    "author": "Calikoglu, Alper",
    "publisher": "Springer International Publishing AG",
    "format": "Paperback / softback",
    "pubDate": "6 Apr 2024",
    "isbn": "9783031269974",
    "dewey": "378.016",
    "rrp": "£139.99",
    "link": "https://www.brownsbfs.co.uk/Product/Calikoglu-Alper/Internationalization-and-the-Academic-Profession/9783031269974"
  },
  {
    "title": "Translation and Own-Language Use in Language Teaching: The Quest for Optimal Practice : The Quest for Optimal Practice",
    "author": "Skopeckova, Eva",
    "publisher": "Palgrave Macmillan",
    "format": "Ebook",
    "pubDate": "6 Apr 2024",
    "isbn": "9783031545412",
    "dewey": "428.0071",
    "rrp": "",
    "link": "https://www.brownsbfs.co.uk/Product/Skopeckova-Eva/Translation-and-Own-Language-Use-in-Language-Teaching-The/9783031545412"
  },
  {
    "title": "Perfect Matchings : A Theory of Matching Covered Graphs",
    "author": "Lucchesi, Claudio L.",
    "publisher": "Springer International Publishing AG",
    "format": "Hardback",
    "pubDate": "6 Apr 2024",
    "isbn": "9783031475030",
    "dewey": "511.66",
    "rrp": "",
    "link": "https://www.brownsbfs.co.uk/Product/Lucchesi-Claudio-L/Perfect-Matchings/9783031475030"
  },
  {
    "title": "The Nature of Ultralong C–C Bonds",
    "author": "Shimajiri, Takuya",
    "publisher": "Springer Verlag, Singapore",
    "format": "Paperback / softback",
    "pubDate": "6 Apr 2024",
    "isbn": "9789819906727",
    "dewey": "541.224",
    "rrp": "£179.99",
    "link": "https://www.brownsbfs.co.uk/Product/Shimajiri-Takuya/The-Nature-of-Ultralong-CC-Bonds/9789819906727"
  },
  {
    "title": "Synthesis of Medium-Sized Cycloalkenes via Fused-Cyclobutenes",
    "author": "Ito, Tomohiro",
    "publisher": "Springer Verlag, Singapore",
    "format": "Hardback",
    "pubDate": "6 Apr 2024",
    "isbn": "9789819707867",
    "dewey": "547.4120459",
    "rrp": "£179.99",
    "link": "https://www.brownsbfs.co.uk/Product/Ito-Tomohiro/Synthesis-of-Medium-Sized-Cycloalkenes-via-Fused-Cyclobutenes/9789819707867"
  },
  {
    "title": "Statistical Rock Physics",
    "author": "Korvin, Gabor",
    "publisher": "Springer",
    "format": "Ebook",
    "pubDate": "6 Apr 2024",
    "isbn": "9783031467004",
    "dewey": "552.0011",
    "rrp": "",
    "link": "https://www.brownsbfs.co.uk/Product/Korvin-Gabor/Statistical-Rock-Physics/9783031467004"
  },
  {
    "title": "Connexin Hemichannels : Methods and Protocols",
    "author": "Mammano, Fabio",
    "publisher": "Humana",
    "format": "Hardback",
    "pubDate": "6 Apr 2024",
    "isbn": "9781071638415",
    "dewey": "571.60284",
    "rrp": "",
    "link": "https://www.brownsbfs.co.uk/Product/Mammano-Fabio/Connexin-Hemichannels/9781071638415"
  },
  {
    "title": "Aquaculture Ecology",
    "author": "Dong, Shuang-Lin",
    "publisher": "Springer Verlag, Singapore",
    "format": "Paperback / softback",
    "pubDate": "6 Apr 2024",
    "isbn": "9789811954887",
    "dewey": "577.55",
    "rrp": "£179.99",
    "link": "https://www.brownsbfs.co.uk/Product/Dong-Shuang-Lin/Aquaculture-Ecology/9789811954887"
  },
  {
    "title": "Nanomaterials for Biomedical and Bioengineering Applications",
    "author": "Javed, Rabia",
    "publisher": "Springer Verlag, Singapore",
    "format": "Hardback",
    "pubDate": "6 Apr 2024",
    "isbn": "9789819702206",
    "dewey": "610.28",
    "rrp": "£199.99",
    "link": "https://www.brownsbfs.co.uk/Product/Javed-Rabia/Nanomaterials-for-Biomedical-and-Bioengineering-Applications/9789819702206"
  },
  {
    "title": "Von Hippel-Lindau Disease : A Comprehensive Guide to Diagnosis, Treatment, and Management",
    "author": "Patel, Dhaval Thakor",
    "publisher": "Springer International Publishing AG",
    "format": "Paperback / softback",
    "pubDate": "6 Apr 2024",
    "isbn": "9783031538575",
    "dewey": "616.042",
    "rrp": "£34.99",
    "link": "https://www.brownsbfs.co.uk/Product/Patel-Dhaval-Thakor/Von-Hippel-Lindau-Disease/9783031538575"
  },
  {
    "title": "Radiation Safety in Nuclear Medicine : A Practical, Concise Guide",
    "author": "Saha, Gopal B.",
    "publisher": "Springer International Publishing AG",
    "format": "Paperback / softback",
    "pubDate": "6 Apr 2024",
    "isbn": "9783031246111",
    "dewey": "616.07575",
    "rrp": "£74.99",
    "link": "https://www.brownsbfs.co.uk/Product/Saha-Gopal-B/Radiation-Safety-in-Nuclear-Medicine/9783031246111"
  },
  {
    "title": "Reprogramming the Brain : A Guide to the Future of the Brain and Neuromodulation by a Patient and his Doctor",
    "author": "Stecher, Benjamin",
    "publisher": "Springer International Publishing AG",
    "format": "Paperback / softback",
    "pubDate": "6 Apr 2024",
    "isbn": "9783031503986",
    "dewey": "616.8",
    "rrp": "",
    "link": "https://www.brownsbfs.co.uk/Product/Stecher-Benjamin/Reprogramming-the-Brain/9783031503986"
  },
  {
    "title": "Gasotransmitters in Organ Transplantation : A New Era in Transplant Medicine",
    "author": "Dugbartey, George J.",
    "publisher": "Springer International Publishing AG",
    "format": "Hardback",
    "pubDate": "6 Apr 2024",
    "isbn": "9783031480669",
    "dewey": "617.954",
    "rrp": "£119.99",
    "link": "https://www.brownsbfs.co.uk/Product/Dugbartey-George-J/Gasotransmitters-in-Organ-Transplantation/9783031480669"
  },
  {
    "title": "Analytical and Numerical Methods for Nonlinear Fluid Flow Problems in Porous Media",
    "author": "Liu, Wenchao",
    "publisher": "Springer Verlag, Singapore",
    "format": "Hardback",
    "pubDate": "6 Apr 2024",
    "isbn": "9789819716340",
    "dewey": "620.116015118",
    "rrp": "£159.99",
    "link": "https://www.brownsbfs.co.uk/Product/Liu-Wenchao/Analytical-and-Numerical-Methods-for-Nonlinear-Fluid-Flow/9789819716340"
  },
  {
    "title": "Low Power Architectures for IoT Applications",
    "author": "Sharma, Devendra Kumar",
    "publisher": "Springer Verlag, Singapore",
    "format": "Paperback / softback",
    "pubDate": "6 Apr 2024",
    "isbn": "9789819906413",
    "dewey": "621.3",
    "rrp": "£149.99",
    "link": "https://www.brownsbfs.co.uk/Product/Sharma-Devendra-Kumar/Low-Power-Architectures-for-IoT-Applications/9789819906413"
  },
  {
    "title": "High Efficiency Non-Isolated DC-DC Converters With Wide Voltage Gain Range for Renewable Energies",
    "author": "Zhang, Yun",
    "publisher": "Springer",
    "format": "Ebook",
    "pubDate": "6 Apr 2024",
    "isbn": "9789819706488",
    "dewey": "621.3132",
    "rrp": "",
    "link": "https://www.brownsbfs.co.uk/Product/Zhang-Yun/High-Efficiency-Non-Isolated-DC-DC-Converters-With-Wide-V/9789819706488"
  },
  {
    "title": "Electroacoustic Waves in Piezoelectric Layered Composites",
    "author": "Avetisyan, Ara Sergey",
    "publisher": "Springer International Publishing AG",
    "format": "Paperback / softback",
    "pubDate": "6 Apr 2024",
    "isbn": "9783031267338",
    "dewey": "621.380412",
    "rrp": "£129.99",
    "link": "https://www.brownsbfs.co.uk/Product/Avetisyan-Ara-Sergey/Electroacoustic-Waves-in-Piezoelectric-Layered-Composites/9783031267338"
  },
  {
    "title": "Mutation Breeding for Sustainable Food Production and Climate Resilience",
    "author": "Penna, Suprasanna",
    "publisher": "Springer Verlag, Singapore",
    "format": "Paperback / softback",
    "pubDate": "6 Apr 2024",
    "isbn": "9789811697227",
    "dewey": "631.53",
    "rrp": "£199.99",
    "link": "https://www.brownsbfs.co.uk/Product/Penna-Suprasanna/Mutation-Breeding-for-Sustainable-Food-Production-and-Climate-Resilience/9789811697227"
  },
  {
    "title": "A Century of Interspecific Hybridization and Introgression in Tobacco",
    "author": "Berbec, Apoloniusz",
    "publisher": "Springer International Publishing AG",
    "format": "Hardback",
    "pubDate": "6 Apr 2024",
    "isbn": "9783031549632",
    "dewey": "633.71233",
    "rrp": "",
    "link": "https://www.brownsbfs.co.uk/Product/Berbec-Apoloniusz/A-Century-of-Interspecific-Hybridization-and-Introgression-in-Tobacco/9783031549632"
  },
  {
    "title": "Capsaicinoids : From Natural Sources to Biosynthesis and their Clinical Applications",
    "author": "Swamy, Mallappa Kumara",
    "publisher": "Springer Verlag, Singapore",
    "format": "Hardback",
    "pubDate": "6 Apr 2024",
    "isbn": "9789819977789",
    "dewey": "633.84",
    "rrp": "",
    "link": "https://www.brownsbfs.co.uk/Product/Swamy-Mallappa-Kumara/Capsaicinoids/9789819977789"
  },
  {
    "title": "Production Diseases in Farm Animals : Pathophysiology, Prophylaxis and Health Management",
    "author": "Gross, Josef Johann",
    "publisher": "Springer International Publishing AG",
    "format": "Hardback",
    "pubDate": "6 Apr 2024",
    "isbn": "9783031517877",
    "dewey": "636.0896",
    "rrp": "",
    "link": "https://www.brownsbfs.co.uk/Product/Gross-Josef-Johann/Production-Diseases-in-Farm-Animals/9783031517877"
  },
  {
    "title": "Blockchain Driven Supply Chain Management : A Multi-dimensional Perspective",
    "author": "Mubarik, Muhammad Shujaat",
    "publisher": "Springer Verlag, Singapore",
    "format": "Paperback / softback",
    "pubDate": "6 Apr 2024",
    "isbn": "9789819907014",
    "dewey": "658.70285574",
    "rrp": "£54.99",
    "link": "https://www.brownsbfs.co.uk/Product/Mubarik-Muhammad-Shujaat/Blockchain-Driven-Supply-Chain-Management/9789819907014"
  },
  {
    "title": "A Comprehensive Approach to Digital Manufacturing",
    "author": "Sirinterlikci, Arif",
    "publisher": "Springer International Publishing AG",
    "format": "Paperback / softback",
    "pubDate": "6 Apr 2024",
    "isbn": "9783031253560",
    "dewey": "670.285",
    "rrp": "£54.99",
    "link": "https://www.brownsbfs.co.uk/Product/Sirinterlikci-Arif/A-Comprehensive-Approach-to-Digital-Manufacturing/9783031253560"
  },
  {
    "title": "The Greatest Westerns Ever Made and the People Who Made Them",
    "author": "Parke, Henry C.",
    "publisher": "TwoDot Books",
    "format": "Paperback / softback",
    "pubDate": "6 Apr 2024",
    "isbn": "9781493074396",
    "dewey": "791.4365878",
    "rrp": "£18.99",
    "link": "https://www.brownsbfs.co.uk/Product/Parke-Henry-C/The-Greatest-Westerns-Ever-Made-and-the-People-Who-Made-Them/9781493074396"
  },
  {
    "title": "Irish Repertory Theatre: Celebrating Thirty-Five Years Off-Broadway : Celebrating Thirty-Five Years Off-Broadway",
    "author": "Szasz, Maria",
    "publisher": "Palgrave Macmillan",
    "format": "Hardback",
    "pubDate": "6 Apr 2024",
    "isbn": "9783031535444",
    "dewey": "792.097471",
    "rrp": "",
    "link": "https://www.brownsbfs.co.uk/Product/Szasz-Maria/Irish-Repertory-Theatre-Celebrating-Thirty-Five-Years-Off-Broadway/9783031535444"
  },
  {
    "title": "Chess puzzles to improve tactical ability, part 2 : for amateurs",
    "author": "Hough, Dewey",
    "publisher": "Independently Published",
    "format": "Paperback / softback",
    "pubDate": "6 Apr 2024",
    "isbn": "9798322084228",
    "dewey": "794.12",
    "rrp": "£8.00",
    "link": "https://www.brownsbfs.co.uk/Product/Hough-Dewey/Chess-puzzles-to-improve-tactical-ability-part-2/9798322084228"
  },
  {
    "title": "Tales of the Yankee Clipper : Stories and Reflections on Joe DiMaggio",
    "author": "Weeks, Jonathan",
    "publisher": "The Lyons Press",
    "format": "Paperback / softback",
    "pubDate": "6 Apr 2024",
    "isbn": "9781493080168",
    "dewey": "796.357092",
    "rrp": "£18.99",
    "link": "https://www.brownsbfs.co.uk/Product/Weeks-Jonathan/Tales-of-the-Yankee-Clipper/9781493080168"
  },
  {
    "title": "Frank Chance's Diamond : The Baseball Journalism of Ring Lardner",
    "author": "Rapoport, Ron",
    "publisher": "The Lyons Press",
    "format": "Paperback / softback",
    "pubDate": "6 Apr 2024",
    "isbn": "9781493080991",
    "dewey": "796.3570973",
    "rrp": "£18.99",
    "link": "https://www.brownsbfs.co.uk/Product/Rapoport-Ron/Frank-Chances-Diamond/9781493080991"
  },
  {
    "title": "New York Mets Firsts : The Players, Moments, and Records That Were First in Team History",
    "author": "Topel, Brett",
    "publisher": "The Lyons Press",
    "format": "Paperback / softback",
    "pubDate": "6 Apr 2024",
    "isbn": "9781493068777",
    "dewey": "796.35764097471",
    "rrp": "£17.99",
    "link": "https://www.brownsbfs.co.uk/Product/Topel-Brett/New-York-Mets-Firsts/9781493068777"
  },
  {
    "title": "The Boston Marathon Handbook : An Insider’s Guide to Training for and Succeeding in the Ultimate Road Race",
    "author": "Pollina, Marc W.",
    "publisher": "Falcon Guides",
    "format": "Paperback / softback",
    "pubDate": "6 Apr 2024",
    "isbn": "9781493079025",
    "dewey": "796.4252071",
    "rrp": "£18.99",
    "link": "https://www.brownsbfs.co.uk/Product/Pollina-Marc-W/The-Boston-Marathon-Handbook/9781493079025"
  },
  {
    "title": "Best Hikes Asheville, North Carolina",
    "author": "Molloy, Johnny",
    "publisher": "Falcon Guides",
    "format": "Paperback / softback",
    "pubDate": "6 Apr 2024",
    "isbn": "9781493075775",
    "dewey": "796.510975688",
    "rrp": "£18.99",
    "link": "https://www.brownsbfs.co.uk/Product/Molloy-Johnny/Best-Hikes-Asheville-North-Carolina/9781493075775"
  },
  {
    "title": "Fishing Yellowstone Waters",
    "author": "Brooks, Charles E.",
    "publisher": "The Lyons Press",
    "format": "Paperback / softback",
    "pubDate": "6 Apr 2024",
    "isbn": "9781493078998",
    "dewey": "799.110978752",
    "rrp": "£19.99",
    "link": "https://www.brownsbfs.co.uk/Product/Brooks-Charles-E/Fishing-Yellowstone-Waters/9781493078998"
  },
  {
    "title": "Joan Wulff's Fly Fishing : Expert Advice from a Woman's Perspective",
    "author": "Wulff, Joan",
    "publisher": "Stackpole Books",
    "format": "Paperback / softback",
    "pubDate": "6 Apr 2024",
    "isbn": "9780811775656",
    "dewey": "799.12",
    "rrp": "£14.99",
    "link": "https://www.brownsbfs.co.uk/Product/Wulff-Joan/Joan-Wulffs-Fly-Fishing/9780811775656"
  },
  {
    "title": "Euro Nymphing : Tips, Tactics, and Techniques",
    "author": "Miller, Josh",
    "publisher": "Stackpole Books",
    "format": "Hardback",
    "pubDate": "6 Apr 2024",
    "isbn": "9780811771221",
    "dewey": "799.124",
    "rrp": "£30.00",
    "link": "https://www.brownsbfs.co.uk/Product/Miller-Josh/Euro-Nymphing/9780811771221"
  }
]